fastkafka2/__init__.py
fastkafka2/py.typed
fastkafka2/api/__init__.py
fastkafka2/api/app.py
fastkafka2/api/handler.py
fastkafka2/api/message.py
fastkafka2/api/producer.py
fastkafka2/core/__init__.py
fastkafka2/core/consumer.py
fastkafka2/core/partition_manager.py
fastkafka2/core/partition_processor.py
fastkafka2/core/rebalance_handler.py
fastkafka2/core/registry.py
fastkafka2/infrastructure/__init__.py
fastkafka2/infrastructure/admin.py
fastkafka2/infrastructure/dependencies.py
fastkafka2/infrastructure/di/__init__.py
fastkafka2/infrastructure/di/di_container.py
fastkafka2/infrastructure/helpers/__init__.py
fastkafka2/infrastructure/helpers/async_client.py
fastkafka2/infrastructure/services/__init__.py
fastkafka2/infrastructure/services/base.py
fastkafka2/infrastructure/services/retry.py
fastkafka2/shared/__init__.py
fastkafka2/shared/logging_utils.py
fastkafka2/shared/serialization.py
fastkafka2-0.3.9.dist-info/licenses/LICENSE
fastkafka2-0.3.9.dist-info/METADATA
fastkafka2-0.3.9.dist-info/WHEEL
fastkafka2-0.3.9.dist-info/top_level.txt
fastkafka2-0.3.9.dist-info/RECORD
