Metadata-Version: 2.4
Name: fastkafka2
Version: 0.3.9
Summary: Next-generation FastAPI-like developer experience for Kafka with async support, lazy deserialization, and built-in Pydantic validation
Author: Ruslan Kiradiev
License-Expression: MIT
Keywords: kafka,async,fastapi,pydantic,microservices,messaging,event-driven
Classifier: Development Status :: 4 - Beta
Classifier: Intended Audience :: Developers
Classifier: Programming Language :: Python :: 3
Classifier: Programming Language :: Python :: 3.10
Classifier: Programming Language :: Python :: 3.11
Classifier: Programming Language :: Python :: 3.12
Classifier: Topic :: Software Development :: Libraries :: Python Modules
Classifier: Topic :: System :: Distributed Computing
Classifier: Topic :: Internet
Classifier: Framework :: AsyncIO
Requires-Python: >=3.10
License-File: LICENSE
Requires-Dist: pydantic
Requires-Dist: confluent-kafka<3,>=2.6
Requires-Dist: typing-extensions>=4.0.0
Requires-Dist: orjson>=3.0.0
Provides-Extra: dev
Requires-Dist: pytest>=7.0.0; extra == "dev"
Requires-Dist: pytest-asyncio>=0.21.0; extra == "dev"
Requires-Dist: black>=23.0.0; extra == "dev"
Requires-Dist: ruff>=0.1.0; extra == "dev"
Requires-Dist: mypy>=1.0.0; extra == "dev"
Dynamic: license-file
